[null,{"name":"sklepik","permissions":"NONE","restriction":"1","actions":[{"info":"1","find":"sklepiki","storage":"1","varName":"kanalxd","name":"Find Channel"},{"info":"0","find":"626867758298038272","storage":"1","varName":"kanal","name":"Find Channel"},{"info":"0","infoIndex":"1","storage":"1","varName":"nazwa","name":"Store Command Params"},{"info":"1","infoIndex":"2","storage":"1","varName":"powod","name":"Store Command Params"},{"member":"0","varName":"","info":"22","storage":"1","varName2":"sklepik","name":"Store Member Info"},{"member":"1","varName":"","info":"16","storage":"1","varName2":"xdd","name":"Store Member Info"},{"title":"**SKLEPIK**","author":"","color":"GREEN","url":"","authorIcon":"","authorUrl":"","imageUrl":"","thumbUrl":"${tempVars(\"xdd\")}","timestamp":"true","text":"","year":"","month":"","day":"","hour":"","minute":"","second":"","storage":"1","varName":"essaxd","name":"Create Embed Message"},{"storage":"1","varName":"essaxd","message":"• **Nazwa Sklepiku** ``${tempVars(\"nazwa\")}``\n\n• **Czym będzie się zajmował sklepik** ``${tempVars(\"powod\")}``\n\n${member}","name":"Set Embed Description"},{"storage":"1","varName":"essaxd","message":"FivemHUB","footerIcon":"https://i.imgur.com/bDyHEmK.gif","name":"Set Embed Footer"},{"storage":"1","varName":"essaxd","channel":"5","varName2":"kanalxd","storage3":"0","varName3":"","name":"Send Embed Message"},{"storage":"1","varName":"essaxd","channel":"5","varName2":"kanal","storage3":"0","varName3":"","name":"Send Embed Message"},{"storage":"0","varName":"","name":"Delete Message"}]},{"name":"przyjmij","permissions":"NONE","restriction":"1","actions":[{"title":"**PRZYJĘTE**","author":"","color":"GREEN","url":"","authorIcon":"","authorUrl":"","imageUrl":"","thumbUrl":"https://i.imgur.com/ncrifw4.png","timestamp":"false","text":"","year":"","month":"","day":"","hour":"","minute":"","second":"","storage":"1","varName":"xdd","name":"Create Embed Message"},{"storage":"1","varName":"xdd","message":"${mentionedUser} **Twoje podanie zostało zaakceptowane!**\n\n``Kieruj się instrukcjami od bota na PW``","name":"Set Embed Description"},{"storage":"1","varName":"xdd","message":"FivemHUB","footerIcon":"https://i.imgur.com/bDyHEmK.gif","name":"Set Embed Footer"},{"storage":"1","varName":"xdd","channel":"0","varName2":"","storage3":"0","varName3":"","name":"Send Embed Message"},{"title":"**PRZYJĘTE**","author":"","color":"GREEN","url":"","authorIcon":"","authorUrl":"","imageUrl":"","thumbUrl":"","timestamp":"true","text":"","year":"","month":"","day":"","hour":"","minute":"","second":"","storage":"1","varName":"essaxd","name":"Create Embed Message"},{"storage":"1","varName":"essaxd","message":"**Gratulacje, twoje podanie zostało zaakceptowane\nZgłoś się do  administratora po więcej info**","name":"Set Embed Description"},{"storage":"1","varName":"essaxd","channel":"2","varName2":"","storage3":"0","varName3":"","name":"Send Embed Message"},{"storage":"0","varName":"","name":"Delete Message"}]},{"name":"odrzuc","permissions":"NONE","restriction":"1","actions":[{"info":"1","infoIndex":"2","storage":"1","varName":"powod","name":"Store Command Params"},{"title":"**ODRZUĆ**","author":"","color":"RED","url":"","authorIcon":"","authorUrl":"","imageUrl":"","thumbUrl":"https://i.imgur.com/9c6VHGa.png","timestamp":"true","text":"","year":"","month":"","day":"","hour":"","minute":"","second":"","storage":"1","varName":"xdd","name":"Create Embed Message"},{"storage":"1","varName":"xdd","message":"${mentionedUser} **Twoje podanie zostało odrzucone!**\n\n• **Powód** ``${tempVars(\"powod\")}``","name":"Set Embed Description"},{"storage":"1","varName":"xdd","message":"FivemHUB","footerIcon":"https://i.imgur.com/bDyHEmK.gif","name":"Set Embed Footer"},{"storage":"1","varName":"xdd","channel":"0","varName2":"","storage3":"0","varName3":"","name":"Send Embed Message"},{"storage":"0","varName":"","name":"Delete Message"}]},{"name":"ogl","permissions":"KICK_MEMBERS","restriction":"1","actions":[{"info":"1","infoIndex":"1","storage":"1","varName":"jdd","name":"Store Command Params"},{"title":"Ogłoszenie ✏️","author":"","color":"#ffffff","url":"","authorIcon":"","authorUrl":"","imageUrl":"","thumbUrl":"https://i.imgur.com/VjTQwQj.png","timestamp":"true","text":"","year":"","month":"","day":"","hour":"","minute":"","second":"","storage":"1","varName":"xdd","name":"Create Embed Message"},{"storage":"1","varName":"xdd","message":"Dodano nowe **ogłoszenie!**\n\n``${tempVars(\"jdd\")}``","name":"Set Embed Description"},{"storage":"1","varName":"xdd","channel":"0","varName2":"","storage3":"0","varName3":"","name":"Send Embed Message"},{"storage":"0","varName":"","name":"Delete Message"}]},{"name":"kick","permissions":"KICK_MEMBERS","restriction":"1","actions":[{"info":"1","infoIndex":"2","storage":"1","varName":"jdd","name":"Store Command Params"},{"member":"0","varName":"","reason":"","name":"Kick Member"},{"title":"**ZBANOWANY**","author":"","color":"RED","url":"","authorIcon":"","authorUrl":"","imageUrl":"","thumbUrl":"","timestamp":"true","text":"","year":"","month":"","day":"","hour":"","minute":"","second":"","storage":"1","varName":"xdd","name":"Create Embed Message"},{"storage":"1","varName":"","message":"${mentionedUser} został **zbanowany** za **${tempVars(\"jdd\")}**","name":"Set Embed Description"},{"storage":"1","varName":"xdd","channel":"0","varName2":"","storage3":"0","varName3":"","name":"Send Embed Message"},{"storage":"0","varName":"","name":"Delete Message"}]},{"name":"ban","permissions":"BAN_MEMBERS","restriction":"1","actions":[{"info":"1","infoIndex":"2","storage":"1","varName":"jdd","name":"Store Command Params"},{"member":"0","varName":"","reason":"","name":"Ban Member"},{"title":"**ZBANOWANY**","author":"","color":"RED","url":"","authorIcon":"","authorUrl":"","imageUrl":"","thumbUrl":"","timestamp":"true","text":"","year":"","month":"","day":"","hour":"","minute":"","second":"","storage":"1","varName":"xdd","name":"Create Embed Message"},{"storage":"1","varName":"","message":"${mentionedUser} został **zbanowany** za **${tempVars(\"jdd\")}**","name":"Set Embed Description"},{"storage":"1","varName":"xdd","channel":"0","varName2":"","storage3":"0","varName3":"","name":"Send Embed Message"},{"storage":"0","varName":"","name":"Delete Message"}]},{"name":"mute","permissions":"KICK_MEMBERS","restriction":"1","actions":[{"info":"1","infoIndex":"2","storage":"1","varName":"powod","name":"Store Command Params"},{"member":"0","varName":"","info":"16","storage":"1","varName2":"url","name":"Store Member Info"},{"info":"1","find":"Muted","storage":"1","varName":"jdd","name":"Find Role"},{"member":"0","varName2":"","role":"3","varName":"jdd","name":"Add Member Role"},{"title":"**ZMUTOWANY**","author":"","color":"RED","url":"","authorIcon":"","authorUrl":"","imageUrl":"","thumbUrl":"${tempVars(\"url\")}","timestamp":"true","text":"","year":"","month":"","day":"","hour":"","minute":"","second":"","storage":"1","varName":"xdd","name":"Create Embed Message"},{"storage":"1","varName":"xdd","message":"${mentionedUser} został **zmutowany!**\n\n**Powód** ``${tempVars(\"powod\")}``","name":"Set Embed Description"},{"storage":"1","varName":"xdd","channel":"0","varName2":"","storage3":"0","varName3":"","name":"Send Embed Message"},{"storage":"0","varName":"","name":"Delete Message"}]},{"name":"odmutuj","permissions":"KICK_MEMBERS","restriction":"1","actions":[{"member":"0","varName":"","info":"16","storage":"1","varName2":"url","name":"Store Member Info"},{"info":"1","find":"Muted","storage":"1","varName":"jdd","name":"Find Role"},{"member":"0","varName2":"","role":"3","varName":"jdd","name":"Remove Member Role"},{"title":"**ODMUTOWANY**","author":"","color":"GREEN","url":"","authorIcon":"","authorUrl":"","imageUrl":"","thumbUrl":"${tempVars(\"url\")}","timestamp":"true","text":"","year":"","month":"","day":"","hour":"","minute":"","second":"","storage":"1","varName":"xdd","name":"Create Embed Message"},{"storage":"1","varName":"xdd","message":"${mentionedUser} został **odmutowany!**\n\n","name":"Set Embed Description"},{"storage":"1","varName":"xdd","channel":"0","varName2":"","storage3":"0","varName3":"","name":"Send Embed Message"},{"storage":"0","varName":"","name":"Delete Message"}]},{"name":"lock","permissions":"KICK_MEMBERS","restriction":"1","actions":[{"info":"1","infoIndex":"1","storage":"1","varName":"powod","name":"Store Command Params"},{"storage":"0","varName":"","permission":"SEND_MESSAGES","state":"1","name":"Set Channel Permissions"},{"title":"**KANAL ZMUTOWANY**","author":"","color":"RED","url":"","authorIcon":"","authorUrl":"","imageUrl":"","thumbUrl":"https://i.imgur.com/4sIL4Kf.png","timestamp":"true","text":"","year":"","month":"","day":"","hour":"","minute":"","second":"","storage":"1","varName":"xdd","name":"Create Embed Message"},{"storage":"1","varName":"xdd","message":"Kanał ${msg.channel} został **zmutowany!**\n\n**Powód** ``${tempVars(\"powod\")}``\n\n**Przez** ${member}","name":"Set Embed Description"},{"storage":"1","varName":"","message":"","footerIcon":"https://i.imgur.com/6tcxbIg.png","name":"Set Embed Footer"},{"storage":"1","varName":"xdd","channel":"0","varName2":"","storage3":"0","varName3":"","name":"Send Embed Message"},{"storage":"0","varName":"","name":"Delete Message"}]},{"name":"unlock","permissions":"KICK_MEMBERS","restriction":"1","actions":[{"info":"1","infoIndex":"1","storage":"1","varName":"powod","name":"Store Command Params"},{"storage":"0","varName":"","permission":"SEND_MESSAGES","state":"0","name":"Set Channel Permissions"},{"title":"**KANAL ODMUTOWANY**","author":"","color":"GREEN","url":"","authorIcon":"","authorUrl":"","imageUrl":"","thumbUrl":"https://i.imgur.com/YFFKumv.png","timestamp":"true","text":"","year":"","month":"","day":"","hour":"","minute":"","second":"","storage":"1","varName":"xdd","name":"Create Embed Message"},{"storage":"1","varName":"xdd","message":"Kanał ${msg.channel} został **odmutowany!**\n\n**Przez** ${member}","name":"Set Embed Description"},{"storage":"1","varName":"","message":"","footerIcon":"https://i.imgur.com/6tcxbIg.png","name":"Set Embed Footer"},{"storage":"1","varName":"xdd","channel":"0","varName2":"","storage3":"0","varName3":"","name":"Send Embed Message"},{"storage":"0","varName":"","name":"Delete Message"}]},{"name":"pomoc","permissions":"NONE","restriction":"1","actions":[{"title":"**POMOC**","author":"","color":"RANDOM","url":"","authorIcon":"","authorUrl":"","imageUrl":"","thumbUrl":"","timestamp":"true","text":"","year":"","month":"","day":"","hour":"","minute":"","second":"","storage":"1","varName":"xdd","name":"Create Embed Message"},{"storage":"1","varName":"xdd","message":"**!sklepik (nazwa sklepiku) (czym się zajmuje)** → Podanie o sklepik\n||!admin|| → Komendy administracyjne","name":"Set Embed Description"}]},{"name":"admin","permissions":"KICK_MEMBERS","restriction":"1","actions":[{"title":"**ADMIN**","author":"","color":"RANDOM","url":"","authorIcon":"","authorUrl":"","imageUrl":"","thumbUrl":"","timestamp":"true","text":"","year":"","month":"","day":"","hour":"","minute":"","second":"","storage":"1","varName":"xdd","name":"Create Embed Message"},{"storage":"1","varName":"xdd","message":"**!mute** Mutuje gracza\n**!odmutuj** Odmutowuje gracza\n**!lock** Zamyka kanał\n**!unlock** Otwiera kanał\n**!ban** Banuje gracza\n**!kick** Kickuje gracza\n**!ogl** Ogłoszenie\n**!przyjmij** Przyjmuje podanie\n**!odrzuc** Odrzuca podanie","name":"Set Embed Description"},{"storage":"1","varName":"xdd","channel":"1","varName2":"","storage3":"0","varName3":"","name":"Send Embed Message"},{"storage":"1","varName":"","message":"FivemHUB","footerIcon":"https://i.imgur.com/bDyHEmK.gif","name":"Set Embed Footer"},{"storage":"0","varName":"","name":"Delete Message"}]}]